qjson5/__init__.py
qjson5/json5.c
qjson5/json5.h
qjson5/py_json5.c
qjson5/py_json5.cpython-311-x86_64-linux-musl.so
qjson5/py_json5.pyi
qjson5-1.0.3.dist-info/METADATA
qjson5-1.0.3.dist-info/WHEEL
qjson5-1.0.3.dist-info/top_level.txt
qjson5-1.0.3.dist-info/RECORD
qjson5-1.0.3.dist-info/licenses/LICENSE
