Metadata-Version: 2.4
Name: qjson5
Version: 1.0.3
Summary: JSON5 parser for Python written in C.
Home-page: https://github.com/qvecs/qjson5
Author: Quick Vectors
Author-email: felipe@qvecs.com
License: MIT
Project-URL: Bug Tracker, https://github.com/qvecs/qjson5/issues
Project-URL: Source Code, https://github.com/qvecs/qjson5
Classifier: Programming Language :: Python :: 3
Classifier: Programming Language :: C
Classifier: Programming Language :: Python :: Implementation :: CPython
Classifier: License :: OSI Approved :: MIT License
Classifier: Operating System :: OS Independent
Classifier: Topic :: Software Development :: Libraries
Requires-Python: >=3.10
License-File: LICENSE
Provides-Extra: dev
Requires-Dist: pytest; extra == "dev"
Dynamic: author
Dynamic: author-email
Dynamic: classifier
Dynamic: description
Dynamic: description-content-type
Dynamic: home-page
Dynamic: license
Dynamic: license-file
Dynamic: project-url
Dynamic: provides-extra
Dynamic: requires-python
Dynamic: summary
